Metadata-Version: 1.1
Name: specification
Version: 0.3.1
Summary: Python implementaion of the `Specification` pattern
Home-page: https://github.com/mamrhein/specification
Author: Michael Amrhein
Author-email: michael@adrhinum.de
License: BSD
Keywords: specification specification-pattern predicate selection validation
Platform: all
Classifier: Development Status :: 4 - Beta
Classifier: Intended Audience :: Developers
Classifier: License :: OSI Approved :: BSD License
Classifier: Operating System :: OS Independent
Classifier: Programming Language :: Python
Classifier: Programming Language :: Python :: 3
Classifier: Programming Language :: Python :: 3.6
Classifier: Programming Language :: Python :: Implementation :: CPython
Classifier: Programming Language :: Python :: Implementation :: PyPy
Classifier: Topic :: Software Development
Classifier: Topic :: Software Development :: Libraries
Classifier: Topic :: Software Development :: Libraries :: Python Modules
